openhunt/__init__.py
openhunt/descriptiveStatistics.py
openhunt/logparser.py
openhunt/mordorutils.py
openhunt/ossem.py
openhunt/utils.py
openhunt/visualizations.py
openhunt-1.8.5.dist-info/METADATA
openhunt-1.8.5.dist-info/WHEEL
openhunt-1.8.5.dist-info/top_level.txt
openhunt-1.8.5.dist-info/RECORD
