Metadata-Version: 2.1
Name: openhunt
Version: 1.8.5
Summary: A Python library to expedite the analysis of data during hunting engagements
Home-page: https://github.com/OTRF/openhunt
Author: Jose Rodriguez @Cyb3rPandaH
License: GNU General Public License v3 (GPLv3)
Keywords: threat hunting python pandas jupyter notebook
Platform: UNKNOWN
Classifier: Development Status :: 4 - Beta
Classifier: Operating System :: OS Independent
Classifier: Topic :: Security
Classifier: Programming Language :: Python :: 3
Classifier: Programming Language :: Python :: 3.3
Classifier: Programming Language :: Python :: 3.4
Classifier: Programming Language :: Python :: 3.5
Classifier: Programming Language :: Python :: 3.6
Classifier: Programming Language :: Python :: 3.7
Requires-Dist: pandas
Requires-Dist: altair
Requires-Dist: seaborn
Requires-Dist: matplotlib
Requires-Dist: pyspark
Requires-Dist: plotly
Requires-Dist: networkx
